NexusViewPro/__init__.py
NexusViewPro/custom_exception.py
NexusViewPro/logger.py
NexusViewPro/site.py
NexusViewPro/youtube.py
nexusviewpro-0.0.2.dist-info/LICENSE
nexusviewpro-0.0.2.dist-info/METADATA
nexusviewpro-0.0.2.dist-info/WHEEL
nexusviewpro-0.0.2.dist-info/top_level.txt
nexusviewpro-0.0.2.dist-info/RECORD
